daq_config_server/__init__.py
daq_config_server/__main__.py
daq_config_server/_version.py
daq_config_server/app.py
daq_config_server/client.py
daq_config_server/config.py
daq_config_server/constants.py
daq_config_server/log.py
daq_config_server/whitelist.py
daq_config_server/testing/__init__.py
daq_config_server/testing/_utils.py
daq_config_server-1.0.0.dist-info/licenses/LICENSE
daq_config_server-1.0.0.dist-info/METADATA
daq_config_server-1.0.0.dist-info/WHEEL
daq_config_server-1.0.0.dist-info/entry_points.txt
daq_config_server-1.0.0.dist-info/top_level.txt
daq_config_server-1.0.0.dist-info/RECORD
