Metadata-Version: 2.4
Name: daq-config-server
Version: 1.0.0
Summary: A service to read files on dls_sw from a blueapi container
Author-email: Oliver Silvester <oliver.silvester@diamond.ac.uk>
License:                                  Apache License
Project-URL: GitHub, https://github.com/DiamondLightSource/daq-config-server
Classifier: Development Status :: 3 - Alpha
Classifier: License :: OSI Approved :: Apache Software License
Classifier: Programming Language :: Python :: 3.11
Classifier: Programming Language :: Python :: 3.12
Classifier: Programming Language :: Python :: 3.13
Requires-Python: >=3.11
License-File: LICENSE
Requires-Dist: pyyaml
Requires-Dist: fastapi
Requires-Dist: uvicorn
Requires-Dist: redis
Requires-Dist: hiredis
Requires-Dist: cachetools
Requires-Dist: graypy
Requires-Dist: pydantic
Requires-Dist: urllib3
Requires-Dist: requests
Provides-Extra: dev
Requires-Dist: copier; extra == "dev"
Requires-Dist: httpx; extra == "dev"
Requires-Dist: mockito; extra == "dev"
Requires-Dist: myst-parser; extra == "dev"
Requires-Dist: pipdeptree; extra == "dev"
Requires-Dist: pre-commit; extra == "dev"
Requires-Dist: pydata-sphinx-theme>=0.12; extra == "dev"
Requires-Dist: pyright; extra == "dev"
Requires-Dist: pytest; extra == "dev"
Requires-Dist: pytest-cov; extra == "dev"
Requires-Dist: pytest-asyncio; extra == "dev"
Requires-Dist: ruff; extra == "dev"
Requires-Dist: sphinx-autobuild; extra == "dev"
Requires-Dist: sphinx-copybutton; extra == "dev"
Requires-Dist: sphinx-design; extra == "dev"
Requires-Dist: tox-direct; extra == "dev"
Requires-Dist: types-mock; extra == "dev"
Dynamic: license-file
